qualitybase/__init__.py
qualitybase/__main__.py
qualitybase/cli.py
qualitybase/decorators.py
qualitybase/commands/__init__.py
qualitybase/commands/args.py
qualitybase/commands/base.py
qualitybase/commands/help.py
qualitybase/commands/varenv.py
qualitybase/commands/version.py
qualitybase/services/__init__.py
qualitybase/services/cli.py
qualitybase/services/dev.py
qualitybase/services/django.py
qualitybase/services/publish.py
qualitybase/services/quality.py
qualitybase/services/utils.py
qualitybase/services/dev/__init__.py
qualitybase/services/dev/build.py
qualitybase/services/dev/clean.py
qualitybase/services/dev/env.py
qualitybase/services/dev/help.py
qualitybase/services/dev/lib.py
qualitybase/services/django/__init__.py
qualitybase/services/django/manage.py
qualitybase/services/publish/__init__.py
qualitybase/services/publish/release.py
qualitybase/services/publish/socialnetwork.py
qualitybase/services/quality/__init__.py
qualitybase/services/quality/cleanup.py
qualitybase/services/quality/complexity.py
qualitybase/services/quality/lint.py
qualitybase/services/quality/security.py
qualitybase/services/quality/test.py
qualitybase/services/service/__init__.py
qualitybase/services/service/help.py
qualitybase/services/service/main.py
qualitybase/services/service/run.py
qualitybase-0.2.4.dist-info/licenses/LICENSE
qualitybase-0.2.4.dist-info/METADATA
qualitybase-0.2.4.dist-info/WHEEL
qualitybase-0.2.4.dist-info/entry_points.txt
qualitybase-0.2.4.dist-info/top_level.txt
qualitybase-0.2.4.dist-info/RECORD
